ID=-1
className=org.apache.zookeeper.server.persistence.FileTxnLog$FileTxnIterator
methodName=FileTxnLog$FileTxnIterator
parameterTypes=java.io.File,long
lineNumber=ENTRY
byteCodeIndex=-1
strategy=stackTrace
variableName=foo

#  public org.apache.zookeeper.server.persistence.FileTxnLog$FileTxnIterator(java.io.File, long) throws java.io.IOException;
#    descriptor: (Ljava/io/File;J)V
#    flags: ACC_PUBLIC
#    Code:
#      stack=3, locals=4, args_size=3
#         0: aload_0
#         1: invokespecial #2                  // Method java/lang/Object."<init>":()V
#         4: aload_0
#         5: aconst_null
#         6: putfield      #3                  // Field inputStream:Lorg/apache/zookeeper/server/persistence/FileTxnLog$PositionInputStream;
#         9: aload_0
#        10: aload_1
#        11: putfield      #4                  // Field logDir:Ljava/io/File;
#        14: aload_0
#        15: lload_2
#        16: putfield      #5                  // Field zxid:J
#        19: aload_0
#        20: invokevirtual #6                  // Method init:()V
#        23: return
#      LineNumberTable:
#        line 504: 0
#        line 493: 4
#        line 505: 9
#        line 506: 14
#        line 507: 19
#        line 508: 23
#      LocalVariableTable:
#        Start  Length  Slot  Name   Signature
#            0      24     0  this   Lorg/apache/zookeeper/server/persistence/FileTxnLog$FileTxnIterator;
#            0      24     1 logDir   Ljava/io/File;
#            0      24     2  zxid   J
