ID=28
className=org.apache.zookeeper.server.persistence.FileTxnLog$FileTxnIterator
methodName=next
parameterTypes=
lineNumber=614
byteCodeIndex=94
variableName=foo
#    0: aload_0
#         1: getfield      #28                 // Field ia:Lorg/apache/jute/InputArchive;
#         4: ifnonnull     9
#         7: iconst_0
#         8: ireturn
#         9: aload_0
#        10: getfield      #28                 // Field ia:Lorg/apache/jute/InputArchive;
#        13: ldc           #60                 // String crcvalue
#        15: invokeinterface #61,  2           // InterfaceMethod org/apache/jute/InputArchive.readLong:(Ljava/lang/String;)J
#        20: lstore_1
#        21: aload_0
#        22: getfield      #28                 // Field ia:Lorg/apache/jute/InputArchive;
#        25: invokestatic  #62                 // Method org/apache/zookeeper/server/persistence/Util.readTxnBytes:(Lorg/apache/jute/InputArchive;)[B
#        28: astore_3
#        29: aload_3
#        30: ifnull        38
#        33: aload_3
#        34: arraylength
#        35: ifne          68
#        38: new           #63                 // class java/io/EOFException
#        41: dup
#        42: new           #36                 // class java/lang/StringBuilder
#        45: dup
#        46: invokespecial #37                 // Method java/lang/StringBuilder."<init>":()V
#        49: ldc           #64                 // String Failed to read
#        51: invokevirtual #39                 // Method java/lang/StringBuilder.append:(Ljava/lang/String;)Ljava/lang/StringBuilder;
#        54: aload_0
#        55: getfield      #26                 // Field logFile:Ljava/io/File;
#        58: invokevirtual #40                 // Method java/lang/StringBuilder.append:(Ljava/lang/Object;)Ljava/lang/StringBuilder;
#        61: invokevirtual #44                 // Method java/lang/StringBuilder.toString:()Ljava/lang/String;
#        64: invokespecial #65                 // Method java/io/EOFException."<init>":(Ljava/lang/String;)V
#        67: athrow
#        68: aload_0
#        69: invokevirtual #66                 // Method makeChecksumAlgorithm:()Ljava/util/zip/Checksum;
#        72: astore        4
#        74: aload         4
#        76: aload_3
#        77: iconst_0
#        78: aload_3
#        79: arraylength
#        80: invokeinterface #67,  4           // InterfaceMethod java/util/zip/Checksum.update:([BII)V
#        85: lload_1
#        86: aload         4
#        88: invokeinterface #68,  1           // InterfaceMethod java/util/zip/Checksum.getValue:()J
#        93: lcmp
#        94: ifeq          107
#        97: new           #35                 // class java/io/IOException
#       100: dup
#       101: ldc           #70                 // String CRC check failed
#       103: invokespecial #45                 // Method java/io/IOException."<init>":(Ljava/lang/String;)V
