ID=3
className=org.apache.zookeeper.server.persistence.FileTxnLog$FileTxnIterator
methodName=goToNextLog
parameterTypes=
lineNumber=ENTRY
byteCodeIndex=-1
strategy=stackTrace
variableName=foo

#  private boolean goToNextLog() throws java.io.IOException;
#     descriptor: ()Z
#     flags: ACC_PRIVATE
#     Code:
#       stack=4, locals=1, args_size=1
#          0: aload_0
#          1: getfield      #9                  // Field storedFiles:Ljava/util/ArrayList;
#          4: invokevirtual #24                 // Method java/util/ArrayList.size:()I
#          7: ifle          47
#         10: aload_0
#         11: aload_0
#         12: getfield      #9                  // Field storedFiles:Ljava/util/ArrayList;
#         15: aload_0
#         16: getfield      #9                  // Field storedFiles:Ljava/util/ArrayList;
#         19: invokevirtual #24                 // Method java/util/ArrayList.size:()I
#         22: iconst_1
#         23: isub
#         24: invokevirtual #25                 // Method java/util/ArrayList.remove:(I)Ljava/lang/Object;
#         27: checkcast     #17                 // class java/io/File
#         30: putfield      #26                 // Field logFile:Ljava/io/File;
#         33: aload_0
#         34: aload_0
#         35: aload_0
#         36: getfield      #26                 // Field logFile:Ljava/io/File;
#         39: invokevirtual #27                 // Method createInputArchive:(Ljava/io/File;)Lorg/apache/jute/InputArchive;
#         42: putfield      #28                 // Field ia:Lorg/apache/jute/InputArchive;
#         45: iconst_1
#         46: ireturn
#         47: iconst_0
#         48: ireturn
#       LineNumberTable:
#         line 544: 0
#         line 545: 10
