ID=2
className=org.apache.zookeeper.server.persistence.FileTxnLog$FileTxnIterator
methodName=init
parameterTypes=
lineNumber=520
byteCodeIndex=76
variableName=foo
strategy=

#  void init() throws java.io.IOException;
#     descriptor: ()V
#     flags:
#     Code:
#       stack=4, locals=4, args_size=1
#          0: aload_0
#          1: new           #7                  // class java/util/ArrayList
#          4: dup
#          5: invokespecial #8                  // Method java/util/ArrayList."<init>":()V
#          8: putfield      #9                  // Field storedFiles:Ljava/util/ArrayList;
#         11: aload_0
#         12: getfield      #4                  // Field logDir:Ljava/io/File;
# 
#       69: iflt          84
#         72: aload_0
#         73: getfield      #9                  // Field storedFiles:Ljava/util/ArrayList;
#         76: aload_3
#         77: invokevirtual #20                 // Method java/util/ArrayList.add:(Ljava/lang/Object;)Z
#         80: pop
#         81: goto          113
#         84: aload_3
#         85: invokevirtual #18                 // Method java/io/File.getName:()Ljava/lang/String;
#         88: ldc           #12                 // String log
#         90: invokestatic  #19                 // Method org/apache/zookeeper/server/persistence/Util.getZxidFromName:(Ljava/lang/String;Ljava/lang/String;)J
#         93: aload_0
#         94: getfield      #5                  // Field zxid:J
#         97: lcmp
#         98: ifge          113
#        101: aload_0
#        102: getfield      #9                  // Field storedFiles:Ljava/util/ArrayList;
#        105: aload_3
#        106: invokevirtual #20                 // Method java/util/ArrayList.add:(Ljava/lang/Object;)Z
#        109: pop
#        110: goto          116
